Fermat/__init__.py
Fermat/fermat.py
Fermat_FasterCoding-1.0.1.dist-info/METADATA
Fermat_FasterCoding-1.0.1.dist-info/WHEEL
Fermat_FasterCoding-1.0.1.dist-info/top_level.txt
Fermat_FasterCoding-1.0.1.dist-info/RECORD
